{
  "frame": {
    "name": "snake-game",
    "version": "1",
    "iconUrl": "https://khalil7044.github.io/snake-game/icon.png",
    "homeUrl": "https://snake-game-one-theta-49.vercel.app/",
    "splashImageUrl": "https://khalil7044.github.io/snake-game/icon.png",
    "splashBackgroundColor": "#667eea",
    "subtitle": "Play the classic snake game",
    "description": "Classic Snake Game - Eat, grow, and don't hit yourself! Challenge your friends and beat the high score.",
    "primaryCategory": "games"
  },
  "accountAssociation": {
    "header": "eyJmaWQiOjE1NDc4LCJ0eXBlIjoiYXV0aCIsImtleSI6IjB4OTI5RjM3YzBDYjZCN0VmYjYyMTdmYzQ2MTk0NGE0OWZjY0NlOEU2OSJ9",
    "payload": "eyJkb21haW4iOiJzbmFrZS1nYW1lLW9uZS10aGV0YS00OS52ZXJjZWwuYXBwIn0",
    "signature": "tLDYrAiE7bBchgvl0T9wJ7YQpwRj0Ln1wDCL8yDu1nMa3A8Za83aWd/yDp7ePKVOqBABlTJL6FYdkoD6MjmKPBw="
  }
}
